easytest/__init__.py
easytest/case.py
easytest/loader.py
easytest/main.py
easytest/producer.py
easytest/result.py
easytest/runner.py
easytest/utils.py
easytest/common/__init__.py
easytest/common/db_handler.py
easytest/common/log_handler.py
easytest/common/test_data_handler.py
lemon_easytest-1.1a4.dist-info/LICENSE
lemon_easytest-1.1a4.dist-info/METADATA
lemon_easytest-1.1a4.dist-info/WHEEL
lemon_easytest-1.1a4.dist-info/entry_points.txt
lemon_easytest-1.1a4.dist-info/top_level.txt
lemon_easytest-1.1a4.dist-info/RECORD
