Metadata-Version: 2.1
Name: lemon-easytest
Version: 1.1a4
Summary: An framework for automated testing interface
Author: xinlan
Author-email: 117220100@qq.com
License: UNKNOWN
Platform: UNKNOWN
Classifier: Programming Language :: Python :: 3.7
Classifier: Programming Language :: Python :: 3.8
Classifier: Programming Language :: Python :: 3.9
Classifier: License :: OSI Approved :: MIT License
Classifier: Operating System :: OS Independent
Requires-Python: >=3.7
License-File: LICENSE
Requires-Dist: pymysql (>=1.0.2)
Requires-Dist: pyyaml (>=6.0)
Requires-Dist: openpyxl (>=3.0.9)
Requires-Dist: requests (>=2.26.0)
Requires-Dist: jsonpath (>=0.82)
Requires-Dist: faker (>=9.7.1)
